docs/__init__.py
docs/md_autogen.py
docs/update_docs.py
texcla/__init__.py
texcla/corpus.py
texcla/data.py
texcla/embeddings.py
texcla/experiment.py
texcla/libs/__init__.py
texcla/libs/fastTextWikiTokenizer/__init__.py
texcla/libs/fastTextWikiTokenizer/subprocess_fix.py
texcla/libs/fastTextWikiTokenizer/tokenize.py
texcla/libs/ngrams/__init__.py
texcla/libs/ngrams/ngrams.py
texcla/libs/twokenize/__init__.py
texcla/libs/twokenize/twokenize.py
texcla/models/__init__.py
texcla/models/layers.py
texcla/models/sentence_model.py
texcla/models/sequence_encoders.py
texcla/models/token_model.py
texcla/preprocessing/__init__.py
texcla/preprocessing/char_tokenizer.py
texcla/preprocessing/sentence_tokenizer.py
texcla/preprocessing/tokenizer.py
texcla/preprocessing/utils.py
texcla/preprocessing/word_tokenizer.py
texcla/utils/__init__.py
texcla/utils/format.py
texcla/utils/generators.py
texcla/utils/io.py
texcla/utils/sampling.py
text_classification_keras-0.1.4.dist-info/LICENSE
text_classification_keras-0.1.4.dist-info/METADATA
text_classification_keras-0.1.4.dist-info/WHEEL
text_classification_keras-0.1.4.dist-info/top_level.txt
text_classification_keras-0.1.4.dist-info/RECORD
