Metadata-Version: 2.1
Name: text-classification-keras
Version: 0.1.4
Summary: Text Classification Library for Keras
Home-page: https://github.com/jfilter/text-classification-keras
Author: Raghavendra Kotikalapudi, Johannes Filter
Author-email: ragha@outlook.com, hi@jfilter.de
License: MIT
Platform: UNKNOWN
Classifier: Topic :: Scientific/Engineering :: Artificial Intelligence
Classifier: Programming Language :: Python :: 3.5
Classifier: Programming Language :: Python :: 3.6
Classifier: Programming Language :: Python :: 2.7
Classifier: License :: OSI Approved :: MIT License
Classifier: Development Status :: 3 - Alpha
Requires-Dist: keras (==2.*)
Requires-Dist: six (==1.*)
Requires-Dist: scikit-learn (==0.*)
Requires-Dist: joblib (==0.*)
Requires-Dist: jsonpickle (==0.*)
Requires-Dist: numpy (==1.*)
Provides-Extra: full
Requires-Dist: spacy (==2.*) ; extra == 'full'
Requires-Dist: deep-plots (==0.*) ; extra == 'full'
Requires-Dist: tensorflow (==1.*) ; extra == 'full'
